gcoordinator/__init__.py
gcoordinator/gcode_generator.py
gcoordinator/gui_export.py
gcoordinator/infill_generator.py
gcoordinator/path_generator.py
gcoordinator/path_transformer.py
gcoordinator/plot_3d.py
gcoordinator/settings.py
gcoordinator/kinematics/kin_base.py
gcoordinator/kinematics/kin_bed_rotate.py
gcoordinator/kinematics/kin_bed_tilt_bc.py
gcoordinator/kinematics/kin_cartesian.py
gcoordinator/kinematics/kin_nozzle_tilt.py
gcoordinator/utils/coords.py
gcoordinator-0.0.15.dist-info/METADATA
gcoordinator-0.0.15.dist-info/WHEEL
gcoordinator-0.0.15.dist-info/licenses/LICENSE
gcoordinator-0.0.15.dist-info/RECORD
