Metadata-Version: 2.1
Name: gcoordinator
Version: 0.0.15
Summary: a package for generate G-code for 3D Printer
Project-URL: Homepage, https://github.com/tomohiron907/gcoordinator
Project-URL: Documentation, https://gcoordinator.readthedocs.io/en/latest/index.html
Author-email: Tomohiro TANIGUCHI <gcoordinator.3dp@gmail.com>
License-File: LICENSE
Classifier: License :: OSI Approved :: MIT License
Classifier: Operating System :: OS Independent
Classifier: Programming Language :: Python :: 3
Requires-Python: >=3.7
Requires-Dist: matplotlib==3.7.1
Requires-Dist: numpy
Requires-Dist: pyopengl
Requires-Dist: pyqt5
Requires-Dist: pyqtgraph==0.13.2
